serverlessworkflow/__init__.py
serverlessworkflow/sdk/__init__.py
serverlessworkflow/sdk/action.py
serverlessworkflow/sdk/action_data_filter.py
serverlessworkflow/sdk/auth_def.py
serverlessworkflow/sdk/basic_props_def.py
serverlessworkflow/sdk/bearer_props_def.py
serverlessworkflow/sdk/branch.py
serverlessworkflow/sdk/branch_timeout.py
serverlessworkflow/sdk/callback_state.py
serverlessworkflow/sdk/callback_state_timeout.py
serverlessworkflow/sdk/continue_as_def.py
serverlessworkflow/sdk/correlation_def.py
serverlessworkflow/sdk/cron_def.py
serverlessworkflow/sdk/databased_switch_state.py
serverlessworkflow/sdk/databased_switch_state_timeout.py
serverlessworkflow/sdk/default_condition_def.py
serverlessworkflow/sdk/end.py
serverlessworkflow/sdk/end_data_condition.py
serverlessworkflow/sdk/end_event_condition.py
serverlessworkflow/sdk/error.py
serverlessworkflow/sdk/error_def.py
serverlessworkflow/sdk/event_based_switch_state.py
serverlessworkflow/sdk/event_based_switch_state_timeout.py
serverlessworkflow/sdk/event_data_filter.py
serverlessworkflow/sdk/event_def.py
serverlessworkflow/sdk/event_ref.py
serverlessworkflow/sdk/event_state.py
serverlessworkflow/sdk/event_state_timeout.py
serverlessworkflow/sdk/foreach_state.py
serverlessworkflow/sdk/foreach_state_timeout.py
serverlessworkflow/sdk/function.py
serverlessworkflow/sdk/function_ref.py
serverlessworkflow/sdk/inject_state.py
serverlessworkflow/sdk/inject_state_timeout.py
serverlessworkflow/sdk/metadata.py
serverlessworkflow/sdk/oauth2props_def.py
serverlessworkflow/sdk/on_events.py
serverlessworkflow/sdk/operation_state.py
serverlessworkflow/sdk/operation_state_timeout.py
serverlessworkflow/sdk/parallel_state.py
serverlessworkflow/sdk/parallel_state_timeout.py
serverlessworkflow/sdk/produce_event_def.py
serverlessworkflow/sdk/retry_def.py
serverlessworkflow/sdk/schedule.py
serverlessworkflow/sdk/serializable.py
serverlessworkflow/sdk/sleep.py
serverlessworkflow/sdk/sleep_state.py
serverlessworkflow.sdk-1.0.0.dist-info/LICENSE
serverlessworkflow.sdk-1.0.0.dist-info/METADATA
serverlessworkflow.sdk-1.0.0.dist-info/WHEEL
serverlessworkflow.sdk-1.0.0.dist-info/top_level.txt
serverlessworkflow.sdk-1.0.0.dist-info/RECORD
