Metadata-Version: 2.1
Name: serverlessworkflow.sdk
Version: 1.0.0
Summary: Serverless Workflow Specification - Python SDK
Home-page: https://serverlessworkflow.io/
Author: Serverless Workflow Contributors
License: http://www.apache.org/licenses/LICENSE-2.0.txt
Platform: UNKNOWN
License-File: LICENSE
Requires-Dist: pyyaml (==6.0)
Requires-Dist: jsonschema (==4.4.0)
Requires-Dist: requests
